[
    {
        "id":1,
        "Author":"Williams Van Smith",
        "Title":"React JS",
        "Published":2018,
        "Branch":"CS and IT",
        "Quantity":25

    },

    {
        "id":2,
        "Author":"Evan Thomas",
        "Title":"Angular TS",
        "Published":2017,
        "Branch":"CS and IT",
        "Quantity":10

    },
    {
        "id":3,
        "Author":"R Ramanujan",
        "Title":"Fundamentals of Math",
        "Published":2018,
        "Branch":"Mathematics",
        "Quantity":22

    },
    
    {
        "id":4,
        "Author":"P Sudha Ranjan",
        "Title":"Machin Learning",
        "Published":2019,
        "Branch":"Mechanical",
        "Quantity":15

    },
    {
        "id":5,
        "Author":"Garry k.",
        "Title":"Elctronics",
        "Published":2020,
        "Branch":"Electrical",
        "Quantity":12

    },
    {
        "id":6,
        "Author":"Sanna Heno",
        "Title":"Engineering Drawing-I",
        "Published":2019,
        "Branch":"Engineering Drawing",
        "Quantity":10

    }
]